{
    "retcode": 0,
    "message": "OK",
    "data": {
        "gacha_type_list": [
            {
                "id": "4",
                "key": "200",
                "name": "常驻祈愿"
            },
            {
                "id": "14",
                "key": "100",
                "name": "新手祈愿"
            },
            {
                "id": "15",
                "key": "301",
                "name": "角色活动祈愿"
            },
            {
                "id": "16",
                "key": "302",
                "name": "武器活动祈愿"
            }
        ],
        "region": "cn_gf01"
    }
}